yumee/__init__.py
yumee/classes/__init__.py
yumee/classes/handlers/__init__.py
yumee/classes/handlers/abstract_song_file_provider.py
yumee/classes/handlers/flac_song_file_provider.py
yumee/classes/handlers/m4a_song_file_provider.py
yumee/classes/handlers/mp3_song_file_provider.py
yumee/classes/handlers/ogg_song_file_provider.py
yumee/classes/handlers/opus_song_file_provider.py
yumee/classes/song_files/__init__.py
yumee/classes/song_files/abstract_song_file.py
yumee/classes/song_files/flac_song_file.py
yumee/classes/song_files/m4a_song_file.py
yumee/classes/song_files/mp3_song_file.py
yumee/classes/song_files/ogg_song_file.py
yumee/classes/song_files/opus_song_file.py
yumee/classes/tools/__init__.py
yumee/classes/tools/lrc_helper.py
yumee/data/__init__.py
yumee/data/song_metadata.py
yumee/data/tag_preset.py
yumee/di/__init__.py
yumee/di/dependency_injector.py
yumee/errors/__init__.py
yumee/errors/song_metadata_error.py
yumee/errors/song_metadata_file_error.py
yumee/interfaces/__init__.py
yumee/interfaces/base_song_file.py
yumee/interfaces/base_song_file_provider.py
yumee/main.py
yumee/py.typed
yumee-0.0.3.dist-info/LICENSE
yumee-0.0.3.dist-info/METADATA
yumee-0.0.3.dist-info/WHEEL
yumee-0.0.3.dist-info/RECORD
