Metadata-Version: 2.1
Name: yumee
Version: 0.0.3
Summary: Yet Unother MEtadata Embedder
Home-page: https://github.com/Billuc/Yumee
License: MIT
Keywords: yumee,song metadata,song,metadata,metadata embedder,python,mp3,m4a,ogg,flac,opus
Author: Billuc
Author-email: billuc@hotmail.fr
Requires-Python: >=3.9,<4.0
Classifier: Intended Audience :: End Users/Desktop
Classifier: License :: OSI Approved :: MIT License
Classifier: Programming Language :: Python
Classifier: Programming Language :: Python :: 3
Classifier: Programming Language :: Python :: 3.9
Classifier: Programming Language :: Python :: 3.10
Classifier: Programming Language :: Python :: 3.11
Classifier: Topic :: Multimedia
Classifier: Topic :: Multimedia :: Sound/Audio
Classifier: Topic :: Utilities
Requires-Dist: mutagen (>=1.46.0,<2.0.0)
Requires-Dist: requests (>=2.31.0,<3.0.0)
Requires-Dist: taipan-di (>=0.0.7,<0.0.8)
Project-URL: Documentation, https://github.com/Billuc/Yumee
Project-URL: Repository, https://github.com/Billuc/Yumee
